AliceNluTrainer/__init__.py
AliceNluTrainer/main.py
projectalice_nlu_trainer-1.2.0.dist-info/LICENSE
projectalice_nlu_trainer-1.2.0.dist-info/METADATA
projectalice_nlu_trainer-1.2.0.dist-info/WHEEL
projectalice_nlu_trainer-1.2.0.dist-info/entry_points.txt
projectalice_nlu_trainer-1.2.0.dist-info/top_level.txt
projectalice_nlu_trainer-1.2.0.dist-info/RECORD
