Metadata-Version: 2.1
Name: projectalice-nlu-trainer
Version: 1.2.0
Summary: Project Alice CLI tool
Home-page: https://github.com/project-alice-assistant/nluTrainer
Author: ProjectAlice
Author-email: laurentchervet@bluewin.ch
Maintainer: Psychokiller1888
License: GPL-3.0
Platform: UNKNOWN
Classifier: Development Status :: 5 - Production/Stable
Classifier: Environment :: Console
Classifier: Intended Audience :: End Users/Desktop
Classifier: License :: OSI Approved :: GNU General Public License v3 (GPLv3)
Classifier: Operating System :: OS Independent
Classifier: Programming Language :: Python :: 3.7
Classifier: Topic :: Home Automation
Classifier: Topic :: System :: Installation/Setup
Requires-Python: ~=3.7
Requires-Dist: click (~=8.0.3)
Requires-Dist: paho-mqtt (~=1.6.1)
Requires-Dist: toml (~=0.10.2)
Requires-Dist: snips-nlu (==0.20.2)
Requires-Dist: pytest (~=6.2.5)
Requires-Dist: coverage (~=6.2)
Requires-Dist: pytest-cov (~=3.0.0)
Requires-Dist: coveralls (~=3.3.1)
